nerfus/download_nerfus_dataset.py
nerfus/run.py
nerfus/bins/binvox
nerfus/cubes/__init__.py
nerfus/cubes/binvox_rw.py
nerfus/cubes/datasets3D.py
nerfus/cubes/render.py
nerfus/cubes/utils.py
nerfus/cubes/visualize3D.py
nerfus/data/.gitkeep
nerfus/data_modules/__init__.py
nerfus/data_modules/cubes3d.py
nerfus/data_modules/datamodule.py
nerfus/lightning/__init__.py
nerfus/lightning/dsds_loss.py
nerfus/lightning/nerfus_trainer.py
nerfus/models/__init__.py
nerfus/models/fp16_util.py
nerfus/models/model.py
nerfus/models/nn.py
nerfus/models/unet.py
nerfus/nerf/nerfbusters_utils.py
nerfus/nerf/nerfus_config.py
nerfus/nerf/nerfus_pipeline.py
nerfus/nerf/experiment_configs/__init__.py
nerfus/nerf/experiment_configs/nerfacto_experiments.py
nerfus/nerf/experiment_configs/utils.py
nerfus/utils/__init__.py
nerfus/utils/metrics.py
nerfus/utils/utils.py
nerfus/utils/visualizations.py
nerfus-0.1.0.dist-info/LICENSE
nerfus-0.1.0.dist-info/METADATA
nerfus-0.1.0.dist-info/WHEEL
nerfus-0.1.0.dist-info/entry_points.txt
nerfus-0.1.0.dist-info/top_level.txt
nerfus-0.1.0.dist-info/RECORD
