Metadata-Version: 2.1
Name: nerfus
Version: 0.1.0
Summary: NeRF-US Removing Ultrasound Imaging Artifacts from Neural Radiance Fields in the Wild
Classifier: Development Status :: 3 - Alpha
Classifier: Programming Language :: Python
Requires-Python: >=3.7.3
License-File: LICENSE
Requires-Dist: diffusers ==0.12.1
Requires-Dist: dotmap
Requires-Dist: trimesh
Requires-Dist: pysdf
Requires-Dist: pytorch-lightning ==1.8.6
Requires-Dist: scipy
Requires-Dist: GPUtil
